doomsday_trainer/__init__.py
doomsday_trainer/__main__.py
doomsday_trainer/dates.py
doomsday_trainer/gui.py
doomsday_trainer/trainer.py
doomsday_trainer-0.4.4.dist-info/entry_points.txt
doomsday_trainer-0.4.4.dist-info/LICENSE
doomsday_trainer-0.4.4.dist-info/WHEEL
doomsday_trainer-0.4.4.dist-info/METADATA
doomsday_trainer-0.4.4.dist-info/RECORD
