Metadata-Version: 2.1
Name: doomsday-trainer
Version: 0.4.4
Summary: Training tool for the Doomsday method.
Home-page: https://github.com/cbernander/doomsday-trainer
License: GPL-3.0-or-later
Author: Christofer Bernander
Requires-Python: >=3.7,<4.0
Classifier: License :: OSI Approved :: GNU General Public License v3 or later (GPLv3+)
Classifier: Programming Language :: Python :: 3
Classifier: Programming Language :: Python :: 3.7
Classifier: Programming Language :: Python :: 3.8
Classifier: Programming Language :: Python :: 3.9
Classifier: Programming Language :: Python :: 3.10
Classifier: Programming Language :: Python :: 3.11
Requires-Dist: pysimplegui (>=4.60.4,<5.0.0)
Project-URL: Repository, https://github.com/cbernander/doomsday-trainer
